annalist/__init__.py
annalist/annalist.py
annalist/decorators.py
data_annalist-0.4.3.dist-info/AUTHORS.rst
data_annalist-0.4.3.dist-info/LICENSE
data_annalist-0.4.3.dist-info/METADATA
data_annalist-0.4.3.dist-info/WHEEL
data_annalist-0.4.3.dist-info/top_level.txt
data_annalist-0.4.3.dist-info/RECORD
