Metadata-Version: 2.1
Name: data-annalist
Version: 0.4.3
Summary: Audit trail generator for data processing scripts.
Author-email: Nic Mostert <nicolas.mostert@horizons.govt.nz>
License: GNU General Public License v3
Project-URL: Homepage, https://github.com/nicmostert/annalist
Project-URL: Issues, https://github.com/nicmostert/annalist/issues
Project-URL: Documentation, https://annalist.readthedocs.io
Project-URL: Package, https://pypi.org/project/data-annalist
Keywords: logging, auditing, audit trail, hydrology, automation, hilltop, hydrobot, HorizonsRC
Classifier: Development Status :: 2 - Pre-Alpha
Classifier: Intended Audience :: Developers
Classifier: License :: OSI Approved :: GNU General Public License v3 (GPLv3)
Classifier: Natural Language :: English
Classifier: Programming Language :: Python :: 3.11
Requires-Python: ==3.11.*
License-File: LICENSE
License-File: AUTHORS.rst
Provides-Extra: all
Requires-Dist: data-annalist[dev,docs,test] ; extra == 'all'
Provides-Extra: dev
Requires-Dist: ruff >=0.1.6 ; extra == 'dev'
Requires-Dist: ruff-lsp >=0.0.45 ; extra == 'dev'
Requires-Dist: pre-commit >=3.5.0 ; extra == 'dev'
Requires-Dist: build >1.0.0 ; extra == 'dev'
Requires-Dist: bump-my-version >=0.17.4 ; extra == 'dev'
Requires-Dist: twine >=5.0.0 ; extra == 'dev'
Provides-Extra: docs
Requires-Dist: Sphinx >=7.2.6 ; extra == 'docs'
Requires-Dist: furo >=2023.9.10 ; extra == 'docs'
Provides-Extra: test
Requires-Dist: pytest >=7.4.2 ; extra == 'test'
Requires-Dist: pytest-cov >=4.1.0 ; extra == 'test'
